adaptable/__init__.py
adaptable/_data_access/__init__.py
adaptable/_data_access/deletion/__init__.py
adaptable/_data_access/deletion/delete_metabase_field_based_on_id.sql
adaptable/_data_access/deletion/delete_metabase_field_based_on_table_id.sql
adaptable/_data_access/deletion/delete_metabase_table_based_on_id.sql
adaptable/_data_access/deletion/delete_metabase_table_based_on_schema_name.sql
adaptable/_data_access/deletion/delete_report_dashboardcard_on_chosen_card_id.sql
adaptable/_data_access/get_dataset_from_db.py
adaptable/_data_access/query/__init__.py
adaptable/_data_access/query/get_metabase_cards_not_recently_looked_at.sql
adaptable/_data_access/query/get_metabase_cards_with_specific_sql_query.sql
adaptable/_data_access/query/get_metabase_dashboard_not_recently_looked_at.sql
adaptable/_data_access/query/get_metabase_field_id.sql
adaptable/_data_access/query/get_metabase_table_id.sql
adaptable/_data_access/update/__init__.py
adaptable/_data_access/update/archive_report_cards_using_id_list.sql
adaptable/_data_access/update/archive_report_dashboards_using_id_list.sql
adaptable/_data_access/update/update_column_name_in_sql_query.sql
adaptable/_data_access/update/update_metabase_field_id_value.sql
adaptable/_data_access/update/update_metabase_table_id_value.sql
adaptable/_data_access/update/update_metabase_table_schema_name.sql
adaptable/_data_access/update/update_table_name_in_metabase_table.sql
adaptable/cleaning/__init__.py
adaptable/cleaning/_utils.py
adaptable/cleaning/archiving.py
adaptable/refactoring/__init__.py
adaptable/refactoring/_utils.py
adaptable/refactoring/reference_system.py
adaptable/refactoring/sql_query.py
adaptable-0.1.7.dist-info/LICENSE.md
adaptable-0.1.7.dist-info/WHEEL
adaptable-0.1.7.dist-info/METADATA
adaptable-0.1.7.dist-info/RECORD
